dispro/__init__.py
dispro/const.py
DisPro-0.1.3.dist-info/LICENSE
DisPro-0.1.3.dist-info/METADATA
DisPro-0.1.3.dist-info/WHEEL
DisPro-0.1.3.dist-info/top_level.txt
DisPro-0.1.3.dist-info/RECORD
