Metadata-Version: 2.1
Name: DisPro
Version: 0.1.3
Summary: A framework for distributed processing applications
Home-page: https://github.com/cmsteffen-code/DisPro
Author: CMSteffen
Author-email: cmsteffen@protonmail.com
License: MIT
Project-URL: Source Code, https://github.com/cmsteffen-code/DisPro
Project-URL: Documentation, https://dispro.readthedocs.io/en/latest/
Keywords: dispro distributed processing framework
Platform: UNKNOWN
Classifier: License :: OSI Approved :: MIT License
Classifier: Programming Language :: Python :: 3
Classifier: Programming Language :: Python :: 3.7
